lodash_py/__init__.py
lodash_py-0.0.4.dist-info/LICENSE
lodash_py-0.0.4.dist-info/METADATA
lodash_py-0.0.4.dist-info/WHEEL
lodash_py-0.0.4.dist-info/top_level.txt
lodash_py-0.0.4.dist-info/RECORD
