Metadata-Version: 2.1
Name: lodash-py
Version: 0.0.4
Summary: Lodash methods in Python.
Home-page: https://github.com/andy19910102/lodash.py
Author: Huang An Sheng
Author-email: andy19910102@gmail.com
Classifier: Programming Language :: Python :: 3
Classifier: License :: OSI Approved :: MIT License
Classifier: Operating System :: OS Independent
Requires-Python: >=3.6
License-File: LICENSE
